Metadata-Version: 2.1
Name: MagiTools
Version: 0.0.1
Summary: MagiTools
Home-page: UNKNOWN
Author: Mag-it
Author-email: rpa@mag-it.com.br
License: MIT License
Keywords: MagiTools
Platform: UNKNOWN
